wellandcanalbridges/__init__.py
wellandcanalbridges-0.2.0.dist-info/licenses/LICENSE.txt
wellandcanalbridges-0.2.0.dist-info/METADATA
wellandcanalbridges-0.2.0.dist-info/WHEEL
wellandcanalbridges-0.2.0.dist-info/top_level.txt
wellandcanalbridges-0.2.0.dist-info/RECORD
